{
  "luops": "2025-10-22T13:28:00+0200",
  "entriesperpage": 10,
  "data": [
    {
      "ac": "A346",
      "lu": "2025-10-22T13:28:00+0200",
      "typ": "P",
      "schalterarea": "12-13",
      "al": "LH",
      "fnr": "LH 422",
      "terminal": "1",
      "halle": "AB",
      "schedArr": "2025-10-22T15:55:00-0500",
      "schalter": "259-335",
      "cs": [
        "UA 8853",
        "AC 9451",
        "SN 7238",
        "TG 7700"
      ],
      "duration": 505,
      "s": false,
      "iata": "BOS",
      "sched": "2025-10-22T13:30:00+0200",
      "reg": "DAIHF",
      "apname": "Boston",
      "id": "d20251022lh422",
      "gate": "Z20",
      "stops": 0,
      "lang": "de",
      "alname": "Lufthansa",
      "flstatus": 3,
      "status": "geschlossen"
    },
    {
      "ac": "A20N",
      "lu": "2025-10-22T13:28:00+0200",
      "typ": "P",
      "schalterarea": "12-13",
      "al": "LH",
      "fnr": "LH 1416",
      "terminal": "1",
      "halle": "AB",
      "schedArr": "2025-10-22T16:50:00+0200",
      "schalter": "259-335",
      "cs": [
        "AC 9153",
        "TP 7610",
        "UA 9402"
      ],
      "duration": 140,
      "s": false,
      "iata": "OTP",
      "sched": "2025-10-22T13:30:00+0200",
      "reg": "DAINB",
      "apname": "Bukarest",
      "id": "d20251022lh1416",
      "gate": "A60",
      "stops": 0,
      "lang": "de",
      "alname": "Lufthansa",
      "flstatus": 3,
      "status": "geschlossen"
    },
    {
      "ac": "A332",
      "lu": "2025-10-22T13:28:00+0200",
      "typ": "P",
      "schalterarea": "14",
      "al": "4Y",
      "fnr": "4Y 076",
      "terminal": "1",
      "halle": "B",
      "schedArr": "2025-10-22T15:05:00-0600",
      "schalter": "476-488",
      "cs": [
        "AC 7392",
        "LH 4404",
        "LX 9314",
        "OS 8465",
        "SN 5672"
      ],
      "duration": 575,
      "s": false,
      "iata": "YYC",
      "sched": "2025-10-22T13:30:00+0200",
      "reg": "DAXGF",
      "apname": "Calgary",
      "id": "d202510224y076",
      "gate": "C13",
      "stops": 0,
      "lang": "de",
      "alname": "Discover Airlines",
      "flstatus": 0,
      "status": "Boarding"
    },
    {
      "ac": "A359",
      "lu": "2025-10-22T13:28:00+0200",
      "typ": "P",
      "schalterarea": "12-13",
      "al": "LH",
      "fnr": "LH 446",
      "terminal": "1",
      "halle": "AB",
      "schedArr": "2025-10-22T15:35:00-0700",
      "schalter": "259-335",
      "cs": [
        "UA 8878"
      ],
      "duration": 605,
      "s": false,
      "iata": "DEN",
      "sched": "2025-10-22T13:30:00+0200",
      "reg": "DAIXG",
      "apname": "Denver",
      "id": "d20251022lh446",
      "gate": "Z64",
      "stops": 0,
      "lang": "de",
      "alname": "Lufthansa",
      "flstatus": 3,
      "status": "geschlossen"
    },
    {
      "ac": "CRJ9",
      "lu": "2025-10-22T13:28:00+0200",
      "typ": "P",
      "schalterarea": "12-13",
      "al": "LH",
      "fnr": "LH 210",
      "terminal": "1",
      "halle": "AB",
      "schedArr": "2025-10-22T14:30:00+0100",
      "schalter": "259-335",
      "cs": [
        "A3 1416",
        "AC 9441",
        "AI 8860",
        "AZ 4710",
        "UA 9052"
      ],
      "duration": 60,
      "s": false,
      "iata": "DRS",
      "sched": "2025-10-22T13:30:00+0200",
      "reg": "DACNC",
      "apname": "Dresden",
      "id": "d20251022lh210",
      "gate": "A4",
      "stops": 0,
      "lang": "de",
      "alname": "Lufthansa",
      "flstatus": 0,
      "status": "Boarding"
    },
    {
      "ac": "A20N",
      "lu": "2025-10-22T13:28:00+0200",
      "typ": "P",
      "schalterarea": "12-13",
      "al": "LH",
      "fnr": "LH 078",
      "terminal": "1",
      "halle": "AB",
      "schedArr": "2025-10-22T14:20:00+0100",
      "schalter": "259-335",
      "cs": [
        "AC 9235",
        "AI 8853",
        "AZ 4724",
        "CA 6037",
        "OU 5412",
        "SQ 2298",
        "UA 8930"
      ],
      "duration": 50,
      "s": false,
      "iata": "DUS",
      "sched": "2025-10-22T13:30:00+0200",
      "reg": "DAINV",
      "apname": "Düsseldorf",
      "id": "d20251022lh078",
      "gate": "B1",
      "stops": 0,
      "lang": "de",
      "alname": "Lufthansa",
      "flstatus": 3,
      "status": "geschlossen"
    },
    {
      "lu": "2025-10-22T13:28:00+0200",
      "typ": "P",
      "oldhalle": "C",
      "schedArr": "2025-10-22T15:45:00+0000",
      "schalter": "656-688",
      "duration": 195,
      "reg": "CSTNM",
      "apname": "Lissabon",
      "id": "d20251022tp571",
      "lang": "de",
      "alname": "TAP Air Portugal",
      "flstatus": 1,
      "ac": "A320",
      "oldgate": "A24",
      "schalterarea": "15",
      "al": "TP",
      "fnr": "TP 571",
      "terminal": "1",
      "halle": "B",
      "cs": [
        "AC 2658",
        "AI 7883",
        "CA 7033",
        "ET 1728",
        "LH 6994",
        "LY 9053",
        "OU 5716",
        "S4 8761",
        "SQ 2792",
        "TG 7307"
      ],
      "s": false,
      "iata": "LIS",
      "sched": "2025-10-22T13:30:00+0200",
      "gate": "A28",
      "stops": 0,
      "status": "Gate offen"
    },
    {
      "ac": "A321",
      "lu": "2025-10-22T13:28:00+0200",
      "typ": "P",
      "schalterarea": "12-13",
      "al": "LH",
      "fnr": "LH 1312",
      "terminal": "1",
      "halle": "AB",
      "schedArr": "2025-10-22T16:05:00+0100",
      "schalter": "259-335",
      "cs": [
        "AC 9269",
        "KM 2305",
        "LO 4849",
        "UA 9054"
      ],
      "duration": 155,
      "s": false,
      "iata": "MLA",
      "sched": "2025-10-22T13:30:00+0200",
      "reg": "DAISG",
      "apname": "Malta",
      "id": "d20251022lh1312",
      "gate": "A50",
      "stops": 0,
      "lang": "de",
      "alname": "Lufthansa",
      "flstatus": 3,
      "status": "geschlossen"
    },
    {
      "ac": "A32A",
      "lu": "2025-10-22T13:28:00+0200",
      "typ": "P",
      "schalterarea": "14",
      "al": "4Y",
      "fnr": "4Y 214",
      "terminal": "1",
      "halle": "B",
      "schedArr": "2025-10-22T15:05:00+0100",
      "schalter": "476-488",
      "cs": [
        "LH 4254"
      ],
      "duration": 150,
      "s": false,
      "iata": "MIR",
      "sched": "2025-10-22T13:35:00+0200",
      "reg": "DAIUV",
      "apname": "Monastir",
      "id": "d202510224y214",
      "gate": "B41",
      "stops": 0,
      "lang": "de",
      "alname": "Discover Airlines",
      "flstatus": 0,
      "status": "Boarding"
    },
    {
      "ac": "A320",
      "lu": "2025-10-22T13:28:00+0200",
      "typ": "P",
      "schalterarea": "12-13",
      "al": "LH",
      "fnr": "LH 1552",
      "terminal": "1",
      "halle": "AB",
      "schedArr": "2025-10-22T15:55:00+0100",
      "schalter": "259-335",
      "duration": 140,
      "s": false,
      "iata": "OVD",
      "sched": "2025-10-22T13:35:00+0200",
      "reg": "DAIZJ",
      "apname": "Asturias",
      "id": "d20251022lh1552",
      "gate": "A69",
      "stops": 0,
      "lang": "de",
      "alname": "Lufthansa",
      "flstatus": 3,
      "status": "geschlossen"
    }
  ],
  "minpage": -187,
  "hasprev": true,
  "page": 1,
  "hasnext": false,
  "type": "departure",
  "results": 85303,
  "lusaison": "2025-10-22T05:15:11+0200",
  "version": "2.4.2",
  "maxpage": 8344
}
